[
    {
        "year": 1990,
        "temp": 53.51
    },
    {
        "year":1991 ,
        "temp": 53.16
    },
    {
        "year":1992 ,
        "temp": 52.6
    },
    {
        "year":1993 ,
        "temp": 51.26
    },
    {
        "year":1994 ,
        "temp": 52.87
    },
    {
        "year": 1995,
        "temp": 52.65
    },
    {
        "year": 1996,
        "temp": 51.88
    },
    {
        "year": 1997,
        "temp": 52.2
    },
    {
        "year": 1998,
        "temp": 54.23
    },
    {
        "year": 1999,
        "temp": 53.88
    },
    {
        "year": 2000,
        "temp": 53.27
    },
    {
        "year": 2001,
        "temp": 53.69
    },
    {
        "year": 2002,
        "temp": 53.21
    },
    {
        "year": 2003,
        "temp": 53.26
    },
    {
        "year": 2004,
        "temp": 53.1
    },
    {
        "year": 2005,
        "temp": 53.64
    },
    {
        "year": 2006,
        "temp": 54.25
    },
    {
        "year": 2007,
        "temp": 53.65
    },
    {
        "year": 2008,
        "temp": 52.29
    },
    {
        "year": 2009,
        "temp": 52.39
    },
    {
        "year": 2010,
        "temp": 52.98
    },
    {
        "year": 2011,
        "temp": 53.18
    },
    {
        "year": 2012,
        "temp": 55.28
    },
    {
        "year": 2013,
        "temp": 52.43
    },
    {
        "year": 2014,
        "temp": 52.54
    },
    {
        "year": 2015,
        "temp": 54.4
    },
    {
        "year": 2016,
        "temp": 54.92
    },
    {
        "year": 2017,
        "temp": 54.55
    },
    {
        "year": 2018,
        "temp": 53.52
    }
]